{
    "xCircle": 61697,
    "x": 61698,
    "wrench": 61699,
    "wifiX": 61700,
    "wifiSlash": 61701,
    "warningCircle": 61702,
    "warning": 61703,
    "wallet": 61704,
    "twitterLogo": 61705,
    "trezorSafe5Filled": 61706,
    "trezorSafe5": 61707,
    "trezorSafe3Filled": 61708,
    "trezorSafe3": 61709,
    "trezorModelTFilled": 61710,
    "trezorModelT": 61711,
    "trezorModelOneFilled": 61712,
    "trezorModelOne": 61713,
    "trezorLogo": 61714,
    "treeStructure": 61715,
    "trashSimple": 61716,
    "swap": 61717,
    "stack": 61718,
    "shuffle": 61719,
    "shieldWarning": 61720,
    "shieldCheck": 61721,
    "shareNetwork": 61722,
    "question": 61723,
    "qrCode": 61724,
    "prohibit": 61725,
    "plusCircle": 61726,
    "plus": 61727,
    "plugs": 61728,
    "piggyBankFilled": 61729,
    "piggyBank": 61730,
    "pictureFrame": 61731,
    "pencilSimpleLine": 61732,
    "pencilSimple": 61733,
    "pencil": 61734,
    "password": 61735,
    "palette": 61736,
    "magnifyingGlass": 61737,
    "lock": 61738,
    "link": 61739,
    "lightbulb": 61740,
    "lifebuoy": 61741,
    "info": 61742,
    "image": 61743,
    "houseFilled": 61744,
    "house": 61745,
    "handPalm": 61746,
    "githubLogo": 61747,
    "gearFilled": 61748,
    "gear": 61749,
    "flagCheckered": 61750,
    "flag": 61751,
    "fingerprintSimple": 61752,
    "fingerprint": 61753,
    "filePdf": 61754,
    "facebookLogo": 61755,
    "eyeSlash": 61756,
    "eye": 61757,
    "discoverFilled": 61758,
    "discover": 61759,
    "detective": 61760,
    "database": 61761,
    "cpu": 61762,
    "copy": 61763,
    "coins": 61764,
    "coinVerticalCheck": 61765,
    "code": 61766,
    "clockClockwise": 61767,
    "circleDashed": 61768,
    "checks": 61769,
    "checkCircleFilled": 61770,
    "checkCircle": 61771,
    "check": 61772,
    "chatCircle": 61773,
    "change": 61774,
    "caretUpFilled": 61775,
    "caretUpDown": 61776,
    "caretUp": 61777,
    "caretRight": 61778,
    "caretLeft": 61779,
    "caretDownFilled": 61780,
    "caretDown": 61781,
    "caretCircleRight": 61782,
    "calendar": 61783,
    "bugBeetle": 61784,
    "bookmarkSimple": 61785,
    "backspace": 61786,
    "arrowsCounterClockwise": 61787,
    "arrowUpRight": 61788,
    "arrowUp": 61789,
    "arrowURightDown": 61790,
    "arrowSquareOut": 61791,
    "arrowRight": 61792,
    "arrowLineUpRight": 61793,
    "arrowLineUp": 61794,
    "arrowLineDown": 61795,
    "arrowDown": 61796
}
